EpicGames_FreeGames_Bot/EpicGamesAutomationApp.py
EpicGames_FreeGames_Bot/EpicGamesConnect.py
EpicGames_FreeGames_Bot/WaitHelper.py
EpicGames_FreeGames_Bot/WebDriverHelper.py
EpicGames_FreeGames_Bot/__init__.py
EpicGames_FreeGames_Bot/main.py
EPICGAMES_FREE_PURCHASE-1.0.dist-info/METADATA
EPICGAMES_FREE_PURCHASE-1.0.dist-info/WHEEL
EPICGAMES_FREE_PURCHASE-1.0.dist-info/entry_points.txt
EPICGAMES_FREE_PURCHASE-1.0.dist-info/top_level.txt
EPICGAMES_FREE_PURCHASE-1.0.dist-info/RECORD
