Metadata-Version: 2.1
Name: EPICGAMES-FREE-PURCHASE
Version: 1.0
Requires-Dist: selenium
Requires-Dist: beautifulsoup4
